python_agents/__init__.py
python_agents/agents.py
python_agents/client.py
python_agents/main.py
python_agents/memory.py
python_agents/message.py
python_agents/tools.py
python_agents/utils.py
python_agents-0.2.0.dist-info/licenses/LICENSE
python_agents-0.2.0.dist-info/METADATA
python_agents-0.2.0.dist-info/WHEEL
python_agents-0.2.0.dist-info/top_level.txt
python_agents-0.2.0.dist-info/RECORD
