Metadata-Version: 2.4
Name: python-agents
Version: 0.2.0
Summary: Easy to use and powerful AI Agent development framework.
Author-email: Michael Anckaert <michael@sinax.be>
Maintainer-email: Michael Anckaert <michael@sinax.be>
License-Expression: Apache-2.0
Project-URL: Repository, https://github.com/MichaelAnckaert/python-agents
Classifier: Development Status :: 4 - Beta
Classifier: Intended Audience :: Developers
Requires-Python: >=3.12
License-File: LICENSE
Requires-Dist: mcp>=1.18.0
Requires-Dist: openai>=2.5.0
Provides-Extra: dev
Requires-Dist: ruff>=0.14.1; extra == "dev"
Provides-Extra: docs
Requires-Dist: sphinx>=7.0.0; extra == "docs"
Requires-Dist: sphinx-rtd-theme>=2.0.0; extra == "docs"
Requires-Dist: sphinx-autodoc-typehints>=2.0.0; extra == "docs"
Dynamic: license-file
